visualize3d/__init__.py
visualize3d/__main__.py
visualize3d/visualize3d.py
visualize3d-1.0.1.dist-info/LICENSE
visualize3d-1.0.1.dist-info/METADATA
visualize3d-1.0.1.dist-info/WHEEL
visualize3d-1.0.1.dist-info/entry_points.txt
visualize3d-1.0.1.dist-info/top_level.txt
visualize3d-1.0.1.dist-info/RECORD
