Metadata-Version: 2.1
Name: visualize3d
Version: 1.0.1
Summary: A library to make 3d visualizations easier.
Home-page: https://github.com/penguinmenac3/visualize3d
Author: Michael Fuerst
Author-email: mail@michaelfuerst.de
License: MIT
Download-URL: https://github.com/penguinmenac3/visualize3d/tarball/1.0.1
Platform: UNKNOWN
Classifier: Development Status :: 3 - Alpha
Classifier: Intended Audience :: Developers
Classifier: Programming Language :: Python
License-File: LICENSE
Requires-Dist: numpy
Requires-Dist: open3d (==0.10.0.0)
Provides-Extra: dev
Requires-Dist: nose2 ; extra == 'dev'
Requires-Dist: packaging ; extra == 'dev'
